README.md
setup.py
shpipes.py
shell_pipes.egg-info/PKG-INFO
shell_pipes.egg-info/SOURCES.txt
shell_pipes.egg-info/dependency_links.txt
shell_pipes.egg-info/top_level.txt