Metadata-Version: 2.1
Name: shell-pipes
Version: 0.1.0
Summary: Extending Python syntax to implement shell commands as pipes using subprocess
Home-page: https://github.com/justquick/shell-pipes
Author: Justin Quick
Author-email: justquick@gmail.com
License: UNKNOWN
Platform: UNKNOWN
Classifier: Programming Language :: Python :: 3
Classifier: Programming Language :: Python :: 2
Classifier: License :: OSI Approved :: MIT License
Classifier: Operating System :: OS Independent
Classifier: Topic :: System :: Shells
Classifier: Programming Language :: Unix Shell
Requires-Python: >=2.7
